papermill_origami/__init__.py
papermill_origami/_version.py
papermill_origami/engine.py
papermill_origami/iorw.py
papermill_origami/noteable_airflow/README.md
papermill_origami/noteable_airflow/__init__.py
papermill_origami/noteable_airflow/operator.py
papermill_origami/noteable_dagstermill/__init__.py
papermill_origami/noteable_dagstermill/assets.py
papermill_origami/noteable_dagstermill/context.py
papermill_origami/noteable_dagstermill/engine.py
papermill_origami/noteable_dagstermill/ops.py
papermill_origami/noteable_dagstermill/translator.py
papermill_origami/noteable_flytekit/__init__.py
papermill_origami/noteable_flytekit/tasks.py
papermill_origami/tests/__init__.py
papermill_origami/tests/conftest.py
papermill_origami/tests/noteable_dagstermill/__init__.py
papermill_origami/tests/test_engine.py
papermill_origami/tests/test_iorw.py
papermill_origami/tests/test_papermill_registration.py
papermill_origami/util.py
papermill_origami-0.0.30.dist-info/LICENSE
papermill_origami-0.0.30.dist-info/METADATA
papermill_origami-0.0.30.dist-info/WHEEL
papermill_origami-0.0.30.dist-info/entry_points.txt
papermill_origami-0.0.30.dist-info/RECORD
