Metadata-Version: 2.1
Name: papermill-origami
Version: 0.0.30
Summary: The noteable API interface
Home-page: https://github.com/noteable-io/papermill-origami
License: BSD-3-Clause
Keywords: notebook,api,noteable
Author: Matt Seal
Author-email: matt@noteable.io
Maintainer: Matt Seal
Maintainer-email: matt@noteable.io
Requires-Python: >=3.8,<4.0
Classifier: Intended Audience :: Developers
Classifier: License :: OSI Approved :: BSD License
Classifier: Programming Language :: Python
Classifier: Programming Language :: Python :: 3
Classifier: Programming Language :: Python :: 3.8
Classifier: Programming Language :: Python :: 3.9
Classifier: Programming Language :: Python :: 3.10
Classifier: Programming Language :: Python :: 3.11
Provides-Extra: airflow
Provides-Extra: dagster
Provides-Extra: flyte
Provides-Extra: prefect
Requires-Dist: apache-airflow (>=2.4.2,<3.0.0) ; extra == "airflow"
Requires-Dist: cloudpickle (>=2.2.0,<3.0.0)
Requires-Dist: dagstermill (>=0.17.6,<0.18.0) ; extra == "dagster"
Requires-Dist: flytekit (>=1.2.1,<2.0.0) ; extra == "flyte"
Requires-Dist: flytekitplugins-papermill (>=1.2.1,<2.0.0) ; extra == "flyte"
Requires-Dist: noteable-origami (>=0.0.35,<0.0.36)
Requires-Dist: papermill (>=2.4.0,<3.0.0)
Requires-Dist: prefect-jupyter (>=0.2.0,<0.3.0) ; extra == "prefect"
Project-URL: Repository, https://github.com/noteable-io/papermill-origami
